source_aircall/__init__.py
source_aircall/manifest.yaml
source_aircall/run.py
source_aircall/schemas/calls.json
source_aircall/schemas/company.json
source_aircall/schemas/contacts.json
source_aircall/schemas/numbers.json
source_aircall/schemas/tags.json
source_aircall/schemas/teams.json
source_aircall/schemas/user_availablity.json
source_aircall/schemas/users.json
source_aircall/schemas/webhooks.json
source_aircall/source.py
source_aircall/spec.yaml
airbyte_source_aircall-0.3.0.dist-info/METADATA
airbyte_source_aircall-0.3.0.dist-info/WHEEL
airbyte_source_aircall-0.3.0.dist-info/entry_points.txt
airbyte_source_aircall-0.3.0.dist-info/RECORD
